graphql_from_struct/__init__.py
graphql_from_struct-1.0.3.dist-info/LICENSE
graphql_from_struct-1.0.3.dist-info/METADATA
graphql_from_struct-1.0.3.dist-info/WHEEL
graphql_from_struct-1.0.3.dist-info/top_level.txt
graphql_from_struct-1.0.3.dist-info/RECORD
