Metadata-Version: 2.1
Name: graphql-from-struct
Version: 1.0.3
Summary: Makes a GraphQL query from Python data structures.
Home-page: https://github.com/artamonoviv/graphql-from-struct
Author: Ivan Artamonov
Author-email: ivan.artamonov.git@gmail.com
License: MIT
Keywords: graphql client dict structure struct web
Platform: any
Classifier: Development Status :: 5 - Production/Stable
Classifier: Intended Audience :: Developers
Classifier: License :: OSI Approved :: MIT License
Classifier: Programming Language :: Python
Classifier: Programming Language :: Python :: 3
Classifier: Programming Language :: Python :: 3.6
Classifier: Programming Language :: Python :: 3.7
Classifier: Programming Language :: Python :: 3.8
Classifier: Topic :: Software Development :: Code Generators
Classifier: Operating System :: OS Independent
Classifier: Topic :: Software Development :: Libraries
Requires-Python: >=3.6
